jax_cuda12_plugin/_hybrid.so
jax_cuda12_plugin/_linalg.so
jax_cuda12_plugin/_mosaic_gpu_ext.so
jax_cuda12_plugin/_prng.so
jax_cuda12_plugin/_rnn.so
jax_cuda12_plugin/_solver.so
jax_cuda12_plugin/_sparse.so
jax_cuda12_plugin/_triton.so
jax_cuda12_plugin/_versions.so
jax_cuda12_plugin/cuda_plugin_extension.so
jax_cuda12_plugin/libmosaic_gpu_runtime.so
jax_cuda12_plugin/version.py
jax_cuda12_plugin-0.9.0.dist-info/METADATA
jax_cuda12_plugin-0.9.0.dist-info/WHEEL
jax_cuda12_plugin-0.9.0.dist-info/top_level.txt
jax_cuda12_plugin-0.9.0.dist-info/RECORD
